pydic/__init__.py
pydic_fdelgados-0.0.8.dist-info/LICENSE.txt
pydic_fdelgados-0.0.8.dist-info/METADATA
pydic_fdelgados-0.0.8.dist-info/WHEEL
pydic_fdelgados-0.0.8.dist-info/top_level.txt
pydic_fdelgados-0.0.8.dist-info/RECORD
