Metadata-Version: 2.1
Name: pydic-fdelgados
Version: 0.0.8
Summary: A simple Dependency Injection Containerf
Home-page: https://github.com/fdelgados/PyDic
Author: Cisco Delgado
Author-email: fdelgados@gmail.com
License: UNKNOWN
Platform: UNKNOWN
Requires-Python: >=3.8
License-File: LICENSE.txt
Requires-Dist: dependency-injector (==4.34.2)
